py4cytoscape/__init__.py
py4cytoscape/_version.py
py4cytoscape/annotations.py
py4cytoscape/apps.py
py4cytoscape/collections.py
py4cytoscape/commands.py
py4cytoscape/cy_ndex.py
py4cytoscape/cytoscape_system.py
py4cytoscape/decorators.py
py4cytoscape/exceptions.py
py4cytoscape/filters.py
py4cytoscape/groups.py
py4cytoscape/layouts.py
py4cytoscape/network_selection.py
py4cytoscape/network_views.py
py4cytoscape/networks.py
py4cytoscape/notebook.py
py4cytoscape/py4cytoscape_logger.py
py4cytoscape/py4cytoscape_logger_settings.py
py4cytoscape/py4cytoscape_notebook.py
py4cytoscape/py4cytoscape_sandbox.py
py4cytoscape/py4cytoscape_tuning.py
py4cytoscape/py4cytoscape_utils.py
py4cytoscape/sandbox.py
py4cytoscape/session.py
py4cytoscape/style_auto_mappings.py
py4cytoscape/style_bypasses.py
py4cytoscape/style_defaults.py
py4cytoscape/style_dependencies.py
py4cytoscape/style_mappings.py
py4cytoscape/style_values.py
py4cytoscape/style_visual_props.py
py4cytoscape/styles.py
py4cytoscape/tables.py
py4cytoscape/tools.py
py4cytoscape/user_interface.py
py4cytoscape/__pycache__/style_bypasses.cpython-310.pyc
py4cytoscape-1.13.0.dist-info/licenses/LICENSE.rst
py4cytoscape-1.13.0.dist-info/METADATA
py4cytoscape-1.13.0.dist-info/WHEEL
py4cytoscape-1.13.0.dist-info/top_level.txt
py4cytoscape-1.13.0.dist-info/RECORD
