Metadata-Version: 2.4
Name: py4cytoscape
Version: 1.13.0
Summary: Cytoscape Automation API
Home-page: https://github.com/cytoscape/py4cytoscape
Author: Barry Demchak
Author-email: bdemchak@ucsd.edu
Maintainer: Barry Demchak
Maintainer-email: bdemchak@ucsd.edu
License: MIT License
Keywords: data visualization,visualization,cytoscape,bioinformatics,graph,network
Classifier: Intended Audience :: Science/Research
Classifier: Intended Audience :: Developers
Classifier: Programming Language :: Python :: 3
Classifier: License :: OSI Approved :: MIT License
Classifier: Operating System :: OS Independent
Classifier: Topic :: Scientific/Engineering :: Bio-Informatics
Classifier: Topic :: Scientific/Engineering :: Information Analysis
Classifier: Topic :: Scientific/Engineering :: Mathematics
Classifier: Topic :: Scientific/Engineering :: Visualization
Requires-Python: >=3.8
License-File: LICENSE.rst
Requires-Dist: pandas
Requires-Dist: networkx
Requires-Dist: requests
Requires-Dist: igraph
Requires-Dist: colorbrewer
Requires-Dist: chardet
Requires-Dist: decorator
Requires-Dist: backoff
Requires-Dist: colour
Dynamic: author
Dynamic: author-email
Dynamic: classifier
Dynamic: description
Dynamic: description-content-type
Dynamic: home-page
Dynamic: keywords
Dynamic: license
Dynamic: license-file
Dynamic: maintainer
Dynamic: maintainer-email
Dynamic: requires-dist
Dynamic: requires-python
Dynamic: summary
